flytekitplugins_whylogs-1.16.12-py3.14-nspkg.pth
flytekitplugins/whylogs/__init__.py
flytekitplugins/whylogs/renderer.py
flytekitplugins/whylogs/schema.py
flytekitplugins_whylogs-1.16.12.dist-info/METADATA
flytekitplugins_whylogs-1.16.12.dist-info/WHEEL
flytekitplugins_whylogs-1.16.12.dist-info/entry_points.txt
flytekitplugins_whylogs-1.16.12.dist-info/namespace_packages.txt
flytekitplugins_whylogs-1.16.12.dist-info/top_level.txt
flytekitplugins_whylogs-1.16.12.dist-info/RECORD
