Metadata-Version: 2.4
Name: flytekitplugins-whylogs
Version: 1.16.12
Summary: Enable the use of whylogs profiles to be used in flyte tasks to get aggregate statistics about data.
Home-page: https://github.com/flyteorg/flytekit/tree/master/plugins/flytekit-whylogs
Author: whylabs
Author-email: support@whylabs.ai
License: apache2
Classifier: Intended Audience :: Science/Research
Classifier: Intended Audience :: Developers
Classifier: License :: OSI Approved :: Apache Software License
Classifier: Programming Language :: Python :: 3.9
Classifier: Programming Language :: Python :: 3.10
Classifier: Topic :: Scientific/Engineering
Classifier: Topic :: Scientific/Engineering :: Artificial Intelligence
Classifier: Topic :: Software Development
Classifier: Topic :: Software Development :: Libraries
Classifier: Topic :: Software Development :: Libraries :: Python Modules
Requires-Python: >=3.9
Requires-Dist: flytekit>=1.3.0b2
Requires-Dist: whylogs[viz]>=1.1.16
Dynamic: author
Dynamic: author-email
Dynamic: classifier
Dynamic: description
Dynamic: description-content-type
Dynamic: home-page
Dynamic: license
Dynamic: requires-dist
Dynamic: requires-python
Dynamic: summary
